{
  "id": "PLQ4IL4UVgQk5G2ow2rn8CwJbPDo0TSPzz",
  "slug": "lets-play-bloons-btd6-s3",
  "title": "Lets Play Bloons BTD6 S3",
  "thumbnail": "https://i.ytimg.com/vi/LjPAuRoQjds/maxresdefault.jpg",
  "published": "2026-02-19T02:21:02.97765Z",
  "updated": "2026-03-17T12:00:46Z",
  "fetched": "2026-03-18T00:03:50.956Z",
  "episodes": 27,
  "duration": 61732,
  "duration_formatted": "17h 8m",
  "duration_short": "17h",
  "views": 1146,
  "views_formatted": "1.1K",
  "status": "Ongoing",
  "status_color": "green"
}